scripts/__init__.py
scripts/add_license.py
scripts/check_license_headers.py
semantiva_studio_viewer-0.2.0.dist-info/METADATA
semantiva_studio_viewer-0.2.0.dist-info/WHEEL
semantiva_studio_viewer-0.2.0.dist-info/entry_points.txt
semantiva_studio_viewer-0.2.0.dist-info/licenses/LICENSE
semantiva_studio_viewer-0.2.0.dist-info/licenses/NOTICE
semantiva_studio_viewer/__init__.py
semantiva_studio_viewer/__main__.py
semantiva_studio_viewer/cli.py
semantiva_studio_viewer/components.py
semantiva_studio_viewer/core_trace_index.py
semantiva_studio_viewer/pipeline.py
semantiva_studio_viewer/runspace_api.py
semantiva_studio_viewer/trace_index_with_runspace.py
semantiva_studio_viewer/web_gui/components.html
semantiva_studio_viewer/web_gui/index.html
semantiva_studio_viewer/web_gui/static/components.css
semantiva_studio_viewer/web_gui/static/components.js
semantiva_studio_viewer/web_gui/static/core/coordinateSystem.js
semantiva_studio_viewer/web_gui/static/pipeline.css
semantiva_studio_viewer/web_gui/static/pipeline.js
semantiva_studio_viewer-0.2.0.dist-info/RECORD
