Metadata-Version: 2.4
Name: semantiva-studio-viewer
Version: 0.2.0
Summary: A standalone package for interactive visualization of Semantiva pipelines and component hierarchies.
License-Expression: Apache-2.0
Requires-Python: >=3.10.12
Requires-Dist: semantiva>=0.5.0rc11
Requires-Dist: fastapi>=0.100.0
Requires-Dist: uvicorn[standard]>=0.20.0
Requires-Dist: httpx>=0.24.0
Requires-Dist: requests>=2.32.5
Requires-Dist: rdflib>=6.0.0
